{"base_happiness":100,"capture_rate":120,"color":{"name":"blue","url":"https://pokeapi.co/api/v2/pokemon-color/2/"},"egg_groups":[{"name":"ground","url":"https://pokeapi.co/api/v2/egg-group/5/"}],"evolution_chain":{"url":"https://pokeapi.co/api/v2/evolution-chain/209/"},"evolves_from_species":{"name":"shinx","url":"https://pokeapi.co/api/v2/pokemon-species/403/"},"flavor_text_entries":[{"flavor_text":"Its claws loose electricity withnenough amperage to cause fainting.nThey live in small groups.","language":{"name":"en","url":"https://pokeapi.co/api/v2/language/9/"},"version":{"name":"diamond","url":"https://pokeapi.co/api/v2/version/12/"}},{"flavor_text":"It rests its forelegs on others toncommunicate with rhythmic electricnpulses from its claws.","language":{"name":"en","url":"https://pokeapi.co/api/v2/language/9/"},"version":{"name":"pearl","url":"https://pokeapi.co/api/v2/version/13/"}},{"flavor_text":"Strong electricity courses throughnthe tips of its sharp claws. A lightnscratch causes fainting in foes.","language":{"name":"en","url":"https://pokeapi.co/api/v2/language/9/"},"version":{"name":"platinum","url":"https://pokeapi.co/api/v2/version/14/"}},{"flavor_text":"By gathering their tails together,nthey collectively generate powerfulnelectricity from their claws. ","language":{"name":"en","url":"https://pokeapi.co/api/v2/language/9/"},"version":{"name":"heartgold","url":"https://pokeapi.co/api/v2/version/15/"}},{"flavor_text":"By gathering their tails together,nthey collectively generate powerfulnelectricity from their claws. ","language":{"name":"en","url":"https://pokeapi.co/api/v2/language/9/"},"version":{"name":"soulsilver","url":"https://pokeapi.co/api/v2/version/16/"}},{"flavor_text":"Le courant qui circule à la pointende ses griffes est capable de fairenperdre connaissance à ses proies.","language":{"name":"fr","url":"https://pokeapi.co/api/v2/language/5/"},"version":{"name":"black","url":"https://pokeapi.co/api/v2/version/17/"}},{"flavor_text":"Strong electricity courses throughnthe tips of its sharp claws. A lightnscratch causes fainting in foes.","language":{"name":"en","url":"https://pokeapi.co/api/v2/language/9/"},"version":{"name":"black","url":"https://pokeapi.co/api/v2/version/17/"}},{"flavor_text":"Le courant qui circule à la pointende ses griffes est capable de fairenperdre connaissance à ses proies.","language":{"name":"fr","url":"https://pokeapi.co/api/v2/language/5/"},"version":{"name":"white","url":"https://pokeapi.co/api/v2/version/18/"}},{"flavor_text":"Strong electricity courses throughnthe tips of its sharp claws. A lightnscratch causes fainting in foes.","language":{"name":"en","url":"https://pokeapi.co/api/v2/language/9/"},"version":{"name":"white","url":"https://pokeapi.co/api/v2/version/18/"}},{"flavor_text":"Strong electricity courses throughnthe tips of its sharp claws. A lightnscratch causes fainting in foes.","language":{"name":"en","url":"https://pokeapi.co/api/v2/language/9/"},"version":{"name":"black-2","url":"https://pokeapi.co/api/v2/version/21/"}},{"flavor_text":"Strong electricity courses throughnthe tips of its sharp claws. A lightnscratch causes fainting in foes.","language":{"name":"en","url":"https://pokeapi.co/api/v2/language/9/"},"version":{"name":"white-2","url":"https://pokeapi.co/api/v2/version/22/"}},{"flavor_text":"いっぱつで　きぜつさせるほどのnでんりゅうを　ツメから　ながす。nすうひきの　グループで　くらす。","language":{"name":"ja-Hrkt","url":"https://pokeapi.co/api/v2/language/1/"},"version":{"name":"x","url":"https://pokeapi.co/api/v2/version/23/"}},{"flavor_text":"발톱에서는 한 방에 적을 기절시킬n정도로 강한 전류가 흐른다.n여러 마리가 그룹을 이루어 산다.","language":{"name":"ko","url":"https://pokeapi.co/api/v2/language/3/"},"version":{"name":"x","url":"https://pokeapi.co/api/v2/version/23/"}},{"flavor_text":"L’électricité libérée par ses griffes peut assommernl’ennemi. Il vit en petits groupes.","language":{"name":"fr","url":"https://pokeapi.co/api/v2/language/5/"},"version":{"name":"x","url":"https://pokeapi.co/api/v2/version/23/"}},{"flavor_text":"Seine Krallen geben Elektrizität ab, die starkngenug ist, jemanden bewusstlos zu machen.","language":{"name":"de","url":"https://pokeapi.co/api/v2/language/6/"},"version":{"name":"x","url":"https://pokeapi.co/api/v2/version/23/"}},{"flavor_text":"Sus garras emiten electricidad que puede debilitar ansus rivales. Viven en grupos pequeños.","language":{"name":"es","url":"https://pokeapi.co/api/v2/language/7/"},"version":{"name":"x","url":"https://pokeapi.co/api/v2/version/23/"}},{"flavor_text":"Dagli artigli rilascia un’elettricità talmente intensanda mandare KO il nemico. Vive in piccoli gruppi.","language":{"name":"it","url":"https://pokeapi.co/api/v2/language/8/"},"version":{"name":"x","url":"https://pokeapi.co/api/v2/version/23/"}},{"flavor_text":"Its claws loose electricity with enough amperagento cause fainting. They live in small groups.","language":{"name":"en","url":"https://pokeapi.co/api/v2/language/9/"},"version":{"name":"x","url":"https://pokeapi.co/api/v2/version/23/"}},{"flavor_text":"１発で　気絶させるほどの　電流をnツメから　流す。n数匹の　グループで　暮らす。","language":{"name":"ja","url":"https://pokeapi.co/api/v2/language/11/"},"version":{"name":"x","url":"https://pokeapi.co/api/v2/version/23/"}},{"flavor_text":"するどい　ツメの　さきには　つよいnでんきが　ながれており　ほんのすこしnかするだけで　あいてをきぜつさせる。","language":{"name":"ja-Hrkt","url":"https://pokeapi.co/api/v2/language/1/"},"version":{"name":"y","url":"https://pokeapi.co/api/v2/version/24/"}},{"flavor_text":"날카로운 발톱의 끝에는 강한n전기가 흐르고 있어서 살짝 스치는n것만으로 상대를 기절시킨다.","language":{"name":"ko","url":"https://pokeapi.co/api/v2/language/3/"},"version":{"name":"y","url":"https://pokeapi.co/api/v2/version/24/"}},{"flavor_text":"Le courant qui circule à la pointe de ses griffes estncapable de faire perdre connaissance à ses proies.","language":{"name":"fr","url":"https://pokeapi.co/api/v2/language/5/"},"version":{"name":"y","url":"https://pokeapi.co/api/v2/version/24/"}},{"flavor_text":"Durch die Spitzen seiner scharfen Krallen strömtnElektrizität. Selbst kleine Kratzer verursachennOhnmacht.","language":{"name":"de","url":"https://pokeapi.co/api/v2/language/6/"},"version":{"name":"y","url":"https://pokeapi.co/api/v2/version/24/"}},{"flavor_text":"Por las puntas de sus garras pasa una fuerte corrienteneléctrica. El mínimo roce debilita al enemigo.","language":{"name":"es","url":"https://pokeapi.co/api/v2/language/7/"},"version":{"name":"y","url":"https://pokeapi.co/api/v2/version/24/"}},{"flavor_text":"I suoi artigli rilasciano una forte corrente elettrica encon un solo graffio manda KO i nemici.","language":{"name":"it","url":"https://pokeapi.co/api/v2/language/8/"},"version":{"name":"y","url":"https://pokeapi.co/api/v2/version/24/"}},{"flavor_text":"Strong electricity courses through the tips of itsnsharp claws. A light scratch causes fainting in foes.","language":{"name":"en","url":"https://pokeapi.co/api/v2/language/9/"},"version":{"name":"y","url":"https://pokeapi.co/api/v2/version/24/"}},{"flavor_text":"鋭い　ツメの　先には　強い　電気がn流れており　ほんの少し　かするだけでn相手を気絶させる。","language":{"name":"ja","url":"https://pokeapi.co/api/v2/language/11/"},"version":{"name":"y","url":"https://pokeapi.co/api/v2/version/24/"}},{"flavor_text":"いっぱつで　きぜつさせるほどのnでんりゅうを　ツメから　ながす。nすうひきの　グループで　くらす。","language":{"name":"ja-Hrkt","url":"https://pokeapi.co/api/v2/language/1/"},"version":{"name":"omega-ruby","url":"https://pokeapi.co/api/v2/version/25/"}},{"flavor_text":"발톱에서는 한 방에 적을 기절시킬n정도로 강한 전류가 흐른다.n여러 마리가 그룹을 이루어 산다.","language":{"name":"ko","url":"https://pokeapi.co/api/v2/language/3/"},"version":{"name":"omega-ruby","url":"https://pokeapi.co/api/v2/version/25/"}},{"flavor_text":"L’électricité libérée par ses griffes peut assommer l’ennemi.nIl vit en petits groupes.","language":{"name":"fr","url":"https://pokeapi.co/api/v2/language/5/"},"version":{"name":"omega-ruby","url":"https://pokeapi.co/api/v2/version/25/"}},{"flavor_text":"Seine Krallen geben Elektrizität ab, die stark genug ist,njemanden bewusstlos zu machen.","language":{"name":"de","url":"https://pokeapi.co/api/v2/language/6/"},"version":{"name":"omega-ruby","url":"https://pokeapi.co/api/v2/version/25/"}},{"flavor_text":"Sus garras emiten electricidad que puede debilitar a susnrivales. Viven en grupos pequeños.","language":{"name":"es","url":"https://pokeapi.co/api/v2/language/7/"},"version":{"name":"omega-ruby","url":"https://pokeapi.co/api/v2/version/25/"}},{"flavor_text":"Dagli artigli rilascia un’elettricità talmente intensa da mandarenKO il nemico. Vive in piccoli gruppi.","language":{"name":"it","url":"https://pokeapi.co/api/v2/language/8/"},"version":{"name":"omega-ruby","url":"https://pokeapi.co/api/v2/version/25/"}},{"flavor_text":"Its claws loose electricity with enough amperagento cause fainting. They live in small groups.","language":{"name":"en","url":"https://pokeapi.co/api/v2/language/9/"},"version":{"name":"omega-ruby","url":"https://pokeapi.co/api/v2/version/25/"}},{"flavor_text":"１発で　気絶させるほどの　電流をnツメから　流す。n数匹の　グループで　暮らす。","language":{"name":"ja","url":"https://pokeapi.co/api/v2/language/11/"},"version":{"name":"omega-ruby","url":"https://pokeapi.co/api/v2/version/25/"}},{"flavor_text":"するどい　ツメの　さきには　つよいnでんきが　ながれており　ほんのすこしnかするだけで　あいてをきぜつさせる。","language":{"name":"ja-Hrkt","url":"https://pokeapi.co/api/v2/language/1/"},"version":{"name":"alpha-sapphire","url":"https://pokeapi.co/api/v2/version/26/"}},{"flavor_text":"날카로운 발톱의 끝에는 강한n전기가 흐르고 있어서 살짝 스치는n것만으로 상대를 기절시킨다.","language":{"name":"ko","url":"https://pokeapi.co/api/v2/language/3/"},"version":{"name":"alpha-sapphire","url":"https://pokeapi.co/api/v2/version/26/"}},{"flavor_text":"Le courant qui circule à la pointe de ses griffes est capablende faire perdre connaissance à ses proies.","language":{"name":"fr","url":"https://pokeapi.co/api/v2/language/5/"},"version":{"name":"alpha-sapphire","url":"https://pokeapi.co/api/v2/version/26/"}},{"flavor_text":"Durch die Spitzen seiner scharfen Krallen strömt Elektrizität.nSelbst kleine Kratzer verursachen Ohnmacht.","language":{"name":"de","url":"https://pokeapi.co/api/v2/language/6/"},"version":{"name":"alpha-sapphire","url":"https://pokeapi.co/api/v2/version/26/"}},{"flavor_text":"Por las puntas de sus garras pasa una fuerte corrienteneléctrica. El mínimo roce debilita al enemigo.","language":{"name":"es","url":"https://pokeapi.co/api/v2/language/7/"},"version":{"name":"alpha-sapphire","url":"https://pokeapi.co/api/v2/version/26/"}},{"flavor_text":"I suoi artigli rilasciano una forte corrente elettrica e connun solo graffio manda KO i nemici.","language":{"name":"it","url":"https://pokeapi.co/api/v2/language/8/"},"version":{"name":"alpha-sapphire","url":"https://pokeapi.co/api/v2/version/26/"}},{"flavor_text":"Strong electricity courses through the tips of itsnsharp claws. A light scratch causes fainting in foes.","language":{"name":"en","url":"https://pokeapi.co/api/v2/language/9/"},"version":{"name":"alpha-sapphire","url":"https://pokeapi.co/api/v2/version/26/"}},{"flavor_text":"鋭い　ツメの　先には　強い　電気がn流れており　ほんの少し　かするだけでn相手を気絶させる。","language":{"name":"ja","url":"https://pokeapi.co/api/v2/language/11/"},"version":{"name":"alpha-sapphire","url":"https://pokeapi.co/api/v2/version/26/"}},{"flavor_text":"しっぽを　つなげて　なかまからnでんきエネルギーを　わけてもらうとnより　つよい　でんげきを　はなてる。","language":{"name":"ja-Hrkt","url":"https://pokeapi.co/api/v2/language/1/"},"version":{"name":"sword","url":"https://pokeapi.co/api/v2/version/33/"}},{"flavor_text":"꼬리를 이어서 동료로부터n전기 에너지를 나눠 받으면n보다 강한 전격을 내보낼 수 있다.","language":{"name":"ko","url":"https://pokeapi.co/api/v2/language/3/"},"version":{"name":"sword","url":"https://pokeapi.co/api/v2/version/33/"}},{"flavor_text":"如果與夥伴尾巴牽尾巴，n就能借用對方的電能，n然後發出更強的電擊。","language":{"name":"zh-Hant","url":"https://pokeapi.co/api/v2/language/4/"},"version":{"name":"sword","url":"https://pokeapi.co/api/v2/version/33/"}},{"flavor_text":"En reliant sa queue à celles de ses congénères,nil peut recevoir leur énergie électrique et lancerndes décharges encore plus puissantes.","language":{"name":"fr","url":"https://pokeapi.co/api/v2/language/5/"},"version":{"name":"sword","url":"https://pokeapi.co/api/v2/version/33/"}},{"flavor_text":"Verbindet es seinen Schweif mit dem einesnArtgenossen, absorbiert es einen Teil von dessennElektrizität und teilt stärkere Stromschläge aus.","language":{"name":"de","url":"https://pokeapi.co/api/v2/language/6/"},"version":{"name":"sword","url":"https://pokeapi.co/api/v2/version/33/"}},{"flavor_text":"Al unir la cola con otro congénere, este lentransmite electricidad, lo que aumenta lanpotencia de sus descargas eléctricas.","language":{"name":"es","url":"https://pokeapi.co/api/v2/language/7/"},"version":{"name":"sword","url":"https://pokeapi.co/api/v2/version/33/"}},{"flavor_text":"Se collega la coda con quella dei suoi simili pernricevere energia elettrica, può emettere scarichenelettriche ancora più potenti.","language":{"name":"it","url":"https://pokeapi.co/api/v2/language/8/"},"version":{"name":"sword","url":"https://pokeapi.co/api/v2/version/33/"}},{"flavor_text":"By joining its tail with that of another Luxio, thisnPokémon can receive some of the other Luxio’snelectricity and power up its own electric blasts.","language":{"name":"en","url":"https://pokeapi.co/api/v2/language/9/"},"version":{"name":"sword","url":"https://pokeapi.co/api/v2/version/33/"}},{"flavor_text":"しっぽを　つなげて　仲間からn電気エネルギーを　分けてもらうとnより　強い　電撃を　放てる。","language":{"name":"ja","url":"https://pokeapi.co/api/v2/language/11/"},"version":{"name":"sword","url":"https://pokeapi.co/api/v2/version/33/"}},{"flavor_text":"当把尾巴和伙伴连接在一起时，n可以分享到对方的电能，n从而释放出更加强力的电击。","language":{"name":"zh-Hans","url":"https://pokeapi.co/api/v2/language/12/"},"version":{"name":"sword","url":"https://pokeapi.co/api/v2/version/33/"}},{"flavor_text":"てきに　であうと　１００まんボルトのnいりょくを　もつ　ツメを　あしからnだして　たたかいに　そなえる。","language":{"name":"ja-Hrkt","url":"https://pokeapi.co/api/v2/language/1/"},"version":{"name":"shield","url":"https://pokeapi.co/api/v2/version/34/"}},{"flavor_text":"적을 만나면 100만 볼트의n위력을 가진 발톱을n드러내어 싸움에 대비한다.","language":{"name":"ko","url":"https://pokeapi.co/api/v2/language/3/"},"version":{"name":"shield","url":"https://pokeapi.co/api/v2/version/34/"}},{"flavor_text":"遇見敵人時會從腳伸出n有百萬伏特威力的爪子，n為對戰做好準備。","language":{"name":"zh-Hant","url":"https://pokeapi.co/api/v2/language/4/"},"version":{"name":"shield","url":"https://pokeapi.co/api/v2/version/34/"}},{"flavor_text":"Quand il croise un ennemi, il se préparenau combat en sortant ses griffes dont les coupsnont une puissance qui atteint un million de volts.","language":{"name":"fr","url":"https://pokeapi.co/api/v2/language/5/"},"version":{"name":"shield","url":"https://pokeapi.co/api/v2/version/34/"}},{"flavor_text":"Sieht es Gegner, macht es sich kampfbereit,nindem es die Krallen an den Pfoten ausfährt,nwelche eine Million Volt austeilen können.","language":{"name":"de","url":"https://pokeapi.co/api/v2/language/6/"},"version":{"name":"shield","url":"https://pokeapi.co/api/v2/version/34/"}},{"flavor_text":"Cuando encuentra a un adversario, se preparanpara combatir sacando las garras, que emitennuna corriente eléctrica de un millón de voltios.","language":{"name":"es","url":"https://pokeapi.co/api/v2/language/7/"},"version":{"name":"shield","url":"https://pokeapi.co/api/v2/version/34/"}},{"flavor_text":"Se incontra un nemico, si prepara alla lottanestraendo gli artigli dotati di una potenza parina 1 milione di volt.","language":{"name":"it","url":"https://pokeapi.co/api/v2/language/8/"},"version":{"name":"shield","url":"https://pokeapi.co/api/v2/version/34/"}},{"flavor_text":"Upon encountering an opponent, this Pokémonnprepares for battle by extending its claws, whichncan put out 1,000,000 volts of electricity.","language":{"name":"en","url":"https://pokeapi.co/api/v2/language/9/"},"version":{"name":"shield","url":"https://pokeapi.co/api/v2/version/34/"}},{"flavor_text":"敵に　出会うと　１００万ボルトのn威力を　もつ　ツメを　足から　だしてn戦いに　備える。","language":{"name":"ja","url":"https://pokeapi.co/api/v2/language/11/"},"version":{"name":"shield","url":"https://pokeapi.co/api/v2/version/34/"}},{"flavor_text":"遇到敌人时会从脚n伸出有着百万伏特n威力的爪子来迎战。","language":{"name":"zh-Hans","url":"https://pokeapi.co/api/v2/language/12/"},"version":{"name":"shield","url":"https://pokeapi.co/api/v2/version/34/"}}],"form_descriptions":[],"forms_switchable":false,"gender_rate":4,"genera":[{"genus":"でんこうポケモン","language":{"name":"ja-Hrkt","url":"https://pokeapi.co/api/v2/language/1/"}},{"genus":"전광포켓몬","language":{"name":"ko","url":"https://pokeapi.co/api/v2/language/3/"}},{"genus":"電光寶可夢","language":{"name":"zh-Hant","url":"https://pokeapi.co/api/v2/language/4/"}},{"genus":"Pokémon Étincelle","language":{"name":"fr","url":"https://pokeapi.co/api/v2/language/5/"}},{"genus":"Funken","language":{"name":"de","url":"https://pokeapi.co/api/v2/language/6/"}},{"genus":"Pokémon Chispa","language":{"name":"es","url":"https://pokeapi.co/api/v2/language/7/"}},{"genus":"Pokémon Favilla","language":{"name":"it","url":"https://pokeapi.co/api/v2/language/8/"}},{"genus":"Spark Pokémon","language":{"name":"en","url":"https://pokeapi.co/api/v2/language/9/"}},{"genus":"でんこうポケモン","language":{"name":"ja","url":"https://pokeapi.co/api/v2/language/11/"}},{"genus":"电光宝可梦","language":{"name":"zh-Hans","url":"https://pokeapi.co/api/v2/language/12/"}}],"generation":{"name":"generation-iv","url":"https://pokeapi.co/api/v2/generation/4/"},"growth_rate":{"name":"medium-slow","url":"https://pokeapi.co/api/v2/growth-rate/4/"},"habitat":null,"has_gender_differences":true,"hatch_counter":20,"id":404,"is_baby":false,"is_legendary":false,"is_mythical":false,"name":"luxio","names":[{"language":{"name":"ja-Hrkt","url":"https://pokeapi.co/api/v2/language/1/"},"name":"ルクシオ"},{"language":{"name":"roomaji","url":"https://pokeapi.co/api/v2/language/2/"},"name":"Luxio"},{"language":{"name":"ko","url":"https://pokeapi.co/api/v2/language/3/"},"name":"럭시오"},{"language":{"name":"zh-Hant","url":"https://pokeapi.co/api/v2/language/4/"},"name":"勒克貓"},{"language":{"name":"fr","url":"https://pokeapi.co/api/v2/language/5/"},"name":"Luxio"},{"language":{"name":"de","url":"https://pokeapi.co/api/v2/language/6/"},"name":"Luxio"},{"language":{"name":"es","url":"https://pokeapi.co/api/v2/language/7/"},"name":"Luxio"},{"language":{"name":"it","url":"https://pokeapi.co/api/v2/language/8/"},"name":"Luxio"},{"language":{"name":"en","url":"https://pokeapi.co/api/v2/language/9/"},"name":"Luxio"},{"language":{"name":"ja","url":"https://pokeapi.co/api/v2/language/11/"},"name":"ルクシオ"},{"language":{"name":"zh-Hans","url":"https://pokeapi.co/api/v2/language/12/"},"name":"勒克猫"}],"order":434,"pal_park_encounters":[{"area":{"name":"field","url":"https://pokeapi.co/api/v2/pal-park-area/2/"},"base_score":70,"rate":20}],"pokedex_numbers":[{"entry_number":404,"pokedex":{"name":"national","url":"https://pokeapi.co/api/v2/pokedex/1/"}},{"entry_number":18,"pokedex":{"name":"original-sinnoh","url":"https://pokeapi.co/api/v2/pokedex/5/"}},{"entry_number":18,"pokedex":{"name":"extended-sinnoh","url":"https://pokeapi.co/api/v2/pokedex/6/"}},{"entry_number":35,"pokedex":{"name":"conquest-gallery","url":"https://pokeapi.co/api/v2/pokedex/11/"}},{"entry_number":26,"pokedex":{"name":"isle-of-armor","url":"https://pokeapi.co/api/v2/pokedex/28/"}}],"shape":{"name":"quadruped","url":"https://pokeapi.co/api/v2/pokemon-shape/8/"},"varieties":[{"is_default":true,"pokemon":{"name":"luxio","url":"https://pokeapi.co/api/v2/pokemon/404/"}}]}