{"base_happiness":140,"capture_rate":130,"color":{"name":"pink","url":"https://pokeapi.co/api/v2/pokemon-color/6/"},"egg_groups":[{"name":"no-eggs","url":"https://pokeapi.co/api/v2/egg-group/15/"}],"evolution_chain":{"url":"https://pokeapi.co/api/v2/evolution-chain/51/"},"evolves_from_species":null,"flavor_text_entries":[{"flavor_text":"It loves round white things.nIt carries an egg-shaped rock innimitation of CHANSEY.","language":{"name":"en","url":"https://pokeapi.co/api/v2/language/9/"},"version":{"name":"diamond","url":"https://pokeapi.co/api/v2/version/12/"}},{"flavor_text":"It carries a round, egg-shapednrock in its belly pouch and givesnthe rock to its friends.","language":{"name":"en","url":"https://pokeapi.co/api/v2/language/9/"},"version":{"name":"pearl","url":"https://pokeapi.co/api/v2/version/13/"}},{"flavor_text":"It likes to carry around a smallnrock. It may wander around others’nfeet and cause them to stumble.","language":{"name":"en","url":"https://pokeapi.co/api/v2/language/9/"},"version":{"name":"platinum","url":"https://pokeapi.co/api/v2/version/14/"}},{"flavor_text":"It carefully carries a round, white rocknthat it thinks is an egg. It’s botherednby how curly its hair looks.","language":{"name":"en","url":"https://pokeapi.co/api/v2/language/9/"},"version":{"name":"heartgold","url":"https://pokeapi.co/api/v2/version/15/"}},{"flavor_text":"It carefully carries a round, white rocknthat it thinks is an egg. It’s botherednby how curly its hair looks.","language":{"name":"en","url":"https://pokeapi.co/api/v2/language/9/"},"version":{"name":"soulsilver","url":"https://pokeapi.co/api/v2/version/16/"}},{"flavor_text":"Ce Pokémon ne se sépare jamais denson petit caillou et a tendance àntraîner dans les pieds des gens.","language":{"name":"fr","url":"https://pokeapi.co/api/v2/language/5/"},"version":{"name":"black","url":"https://pokeapi.co/api/v2/version/17/"}},{"flavor_text":"It likes to carry around a smallnrock. It may wander around others’nfeet and cause them to stumble.","language":{"name":"en","url":"https://pokeapi.co/api/v2/language/9/"},"version":{"name":"black","url":"https://pokeapi.co/api/v2/version/17/"}},{"flavor_text":"Ce Pokémon ne se sépare jamais denson petit caillou et a tendance àntraîner dans les pieds des gens.","language":{"name":"fr","url":"https://pokeapi.co/api/v2/language/5/"},"version":{"name":"white","url":"https://pokeapi.co/api/v2/version/18/"}},{"flavor_text":"It likes to carry around a smallnrock. It may wander around others’nfeet and cause them to stumble.","language":{"name":"en","url":"https://pokeapi.co/api/v2/language/9/"},"version":{"name":"white","url":"https://pokeapi.co/api/v2/version/18/"}},{"flavor_text":"It likes to carry around a smallnrock. It may wander around others’nfeet and cause them to stumble.","language":{"name":"en","url":"https://pokeapi.co/api/v2/language/9/"},"version":{"name":"black-2","url":"https://pokeapi.co/api/v2/version/21/"}},{"flavor_text":"It likes to carry around a smallnrock. It may wander around others’nfeet and cause them to stumble.","language":{"name":"en","url":"https://pokeapi.co/api/v2/language/9/"},"version":{"name":"white-2","url":"https://pokeapi.co/api/v2/version/22/"}},{"flavor_text":"タマゴに　にた　まんまるい　いしをnおなかの　ふくろに　いれている。nすきな　あいてに　いしを　わたす。","language":{"name":"ja-Hrkt","url":"https://pokeapi.co/api/v2/language/1/"},"version":{"name":"x","url":"https://pokeapi.co/api/v2/version/23/"}},{"flavor_text":"알을 닮은 둥근 돌을n배의 주머니에 넣고 있다.n좋아하는 상대에게 돌을 준다.","language":{"name":"ko","url":"https://pokeapi.co/api/v2/language/3/"},"version":{"name":"x","url":"https://pokeapi.co/api/v2/version/23/"}},{"flavor_text":"Ptiravi transporte un caillou rond en forme d’œuf dansnsa poche ventrale pour l’offrir à ses amis.","language":{"name":"fr","url":"https://pokeapi.co/api/v2/language/5/"},"version":{"name":"x","url":"https://pokeapi.co/api/v2/version/23/"}},{"flavor_text":"In seinem Beutel trägt es einen runden,neiförmigen Stein, den es Freunden gibt.","language":{"name":"de","url":"https://pokeapi.co/api/v2/language/6/"},"version":{"name":"x","url":"https://pokeapi.co/api/v2/version/23/"}},{"flavor_text":"Les da a sus amigos una roca con forma de huevo quentransporta en la bolsa de su panza.","language":{"name":"es","url":"https://pokeapi.co/api/v2/language/7/"},"version":{"name":"x","url":"https://pokeapi.co/api/v2/version/23/"}},{"flavor_text":"Trasporta una roccia a forma di uovo nella suantasca ventrale e poi la offre ai suoi amici.","language":{"name":"it","url":"https://pokeapi.co/api/v2/language/8/"},"version":{"name":"x","url":"https://pokeapi.co/api/v2/version/23/"}},{"flavor_text":"It carries a round, egg-shaped rock in its bellynpouch and gives the rock to its friends.","language":{"name":"en","url":"https://pokeapi.co/api/v2/language/9/"},"version":{"name":"x","url":"https://pokeapi.co/api/v2/version/23/"}},{"flavor_text":"タマゴに　似た　真んまるい　石をnお腹の　袋に　入れている。n好きな　相手に　石を　渡す。","language":{"name":"ja","url":"https://pokeapi.co/api/v2/language/11/"},"version":{"name":"x","url":"https://pokeapi.co/api/v2/version/23/"}},{"flavor_text":"しろくて　まるい　いしを　タマゴとnおもいこんで　だいじに　もっている。nまきげの　かたちを　きにしている。","language":{"name":"ja-Hrkt","url":"https://pokeapi.co/api/v2/language/1/"},"version":{"name":"y","url":"https://pokeapi.co/api/v2/version/24/"}},{"flavor_text":"하얗고 둥근 돌을 알이라고n생각하고는 소중히 가지고 있다.n말려 있는 머리 모양을 신경 쓰고 있다.","language":{"name":"ko","url":"https://pokeapi.co/api/v2/language/3/"},"version":{"name":"y","url":"https://pokeapi.co/api/v2/version/24/"}},{"flavor_text":"Il prend soin de ses bouclettes et couve son caillouncomme si c’était son Œuf.","language":{"name":"fr","url":"https://pokeapi.co/api/v2/language/5/"},"version":{"name":"y","url":"https://pokeapi.co/api/v2/version/24/"}},{"flavor_text":"Es hält den runden, weißen Stein für ein Einund kümmert sich um ihn. Es achtet sehrnauf seine Haarlocke.","language":{"name":"de","url":"https://pokeapi.co/api/v2/language/6/"},"version":{"name":"y","url":"https://pokeapi.co/api/v2/version/24/"}},{"flavor_text":"Cuida de una pequeña roca blanca y redondancreyendo que es un huevo. Le gusta arreglarsenel tirabuzón.","language":{"name":"es","url":"https://pokeapi.co/api/v2/language/7/"},"version":{"name":"y","url":"https://pokeapi.co/api/v2/version/24/"}},{"flavor_text":"Trasporta con cura un sasso bianco e tondontrattandolo come un uovo.nAdora il ricciolo che ha in testa.","language":{"name":"it","url":"https://pokeapi.co/api/v2/language/8/"},"version":{"name":"y","url":"https://pokeapi.co/api/v2/version/24/"}},{"flavor_text":"It carefully carries a round, white rock that it thinksnis an egg. It’s bothered by how curly its hair looks.","language":{"name":"en","url":"https://pokeapi.co/api/v2/language/9/"},"version":{"name":"y","url":"https://pokeapi.co/api/v2/version/24/"}},{"flavor_text":"白くて　まるい　石を　タマゴとn思いこんで　大事に　持っている。n巻き毛の　形を　気にしている。","language":{"name":"ja","url":"https://pokeapi.co/api/v2/language/11/"},"version":{"name":"y","url":"https://pokeapi.co/api/v2/version/24/"}},{"flavor_text":"タマゴに　にた　まんまるい　いしをnおなかの　ふくろに　いれている。nすきな　あいてに　いしを　わたす。","language":{"name":"ja-Hrkt","url":"https://pokeapi.co/api/v2/language/1/"},"version":{"name":"omega-ruby","url":"https://pokeapi.co/api/v2/version/25/"}},{"flavor_text":"알을 닮은 둥근 돌을n배의 주머니에 넣고 있다.n좋아하는 상대에게 돌을 준다.","language":{"name":"ko","url":"https://pokeapi.co/api/v2/language/3/"},"version":{"name":"omega-ruby","url":"https://pokeapi.co/api/v2/version/25/"}},{"flavor_text":"Ptiravi transporte un caillou rond en forme d’œuf dansnsa poche ventrale pour l’offrir à ses amis.","language":{"name":"fr","url":"https://pokeapi.co/api/v2/language/5/"},"version":{"name":"omega-ruby","url":"https://pokeapi.co/api/v2/version/25/"}},{"flavor_text":"In seinem Beutel trägt es einen runden, eiförmigen Stein,nden es Freunden gibt.","language":{"name":"de","url":"https://pokeapi.co/api/v2/language/6/"},"version":{"name":"omega-ruby","url":"https://pokeapi.co/api/v2/version/25/"}},{"flavor_text":"Les da a sus amigos una roca con forma de huevo quentransporta en la bolsa de su panza.","language":{"name":"es","url":"https://pokeapi.co/api/v2/language/7/"},"version":{"name":"omega-ruby","url":"https://pokeapi.co/api/v2/version/25/"}},{"flavor_text":"Trasporta una roccia a forma di uovo nella sua tasca ventralene poi la offre ai suoi amici.","language":{"name":"it","url":"https://pokeapi.co/api/v2/language/8/"},"version":{"name":"omega-ruby","url":"https://pokeapi.co/api/v2/version/25/"}},{"flavor_text":"It carries a round, egg-shaped rock in its bellynpouch and gives the rock to its friends.","language":{"name":"en","url":"https://pokeapi.co/api/v2/language/9/"},"version":{"name":"omega-ruby","url":"https://pokeapi.co/api/v2/version/25/"}},{"flavor_text":"タマゴに　似た　真んまるい　石をnお腹の　袋に　入れている。n好きな　相手に　石を　渡す。","language":{"name":"ja","url":"https://pokeapi.co/api/v2/language/11/"},"version":{"name":"omega-ruby","url":"https://pokeapi.co/api/v2/version/25/"}},{"flavor_text":"しろくて　まるい　いしを　タマゴとnおもいこんで　だいじに　もっている。nまきげの　かたちを　きにしている。","language":{"name":"ja-Hrkt","url":"https://pokeapi.co/api/v2/language/1/"},"version":{"name":"alpha-sapphire","url":"https://pokeapi.co/api/v2/version/26/"}},{"flavor_text":"하얗고 둥근 돌을 알이라고n생각하고는 소중히 가지고 있다.n말려 있는 머리 모양을 신경 쓰고 있다.","language":{"name":"ko","url":"https://pokeapi.co/api/v2/language/3/"},"version":{"name":"alpha-sapphire","url":"https://pokeapi.co/api/v2/version/26/"}},{"flavor_text":"Il prend soin de ses bouclettes et couve son caillou commensi c’était son Œuf.","language":{"name":"fr","url":"https://pokeapi.co/api/v2/language/5/"},"version":{"name":"alpha-sapphire","url":"https://pokeapi.co/api/v2/version/26/"}},{"flavor_text":"Es hält den runden, weißen Stein für ein Ei und kümmert sichnum ihn. Es achtet sehr auf seine Haarlocke.","language":{"name":"de","url":"https://pokeapi.co/api/v2/language/6/"},"version":{"name":"alpha-sapphire","url":"https://pokeapi.co/api/v2/version/26/"}},{"flavor_text":"Cuida de una pequeña roca blanca y redonda creyendo quenes un huevo. Le gusta arreglarse el tirabuzón.","language":{"name":"es","url":"https://pokeapi.co/api/v2/language/7/"},"version":{"name":"alpha-sapphire","url":"https://pokeapi.co/api/v2/version/26/"}},{"flavor_text":"Trasporta con cura un sasso bianco e tondo trattandoloncome un uovo. Adora il ricciolo che ha in testa.","language":{"name":"it","url":"https://pokeapi.co/api/v2/language/8/"},"version":{"name":"alpha-sapphire","url":"https://pokeapi.co/api/v2/version/26/"}},{"flavor_text":"It carefully carries a round, white rock that it thinksnis an egg. It’s bothered by how curly its hair looks.","language":{"name":"en","url":"https://pokeapi.co/api/v2/language/9/"},"version":{"name":"alpha-sapphire","url":"https://pokeapi.co/api/v2/version/26/"}},{"flavor_text":"白くて　まるい　石を　タマゴとn思いこんで　大事に　持っている。n巻き毛の　形を　気にしている。","language":{"name":"ja","url":"https://pokeapi.co/api/v2/language/11/"},"version":{"name":"alpha-sapphire","url":"https://pokeapi.co/api/v2/version/26/"}},{"flavor_text":"おなかの　ふくろに　しろくて　まるいnいしを　いれている。　なかよくなるとnわけて　くれることも　あるよ。","language":{"name":"ja-Hrkt","url":"https://pokeapi.co/api/v2/language/1/"},"version":{"name":"sun","url":"https://pokeapi.co/api/v2/version/27/"}},{"flavor_text":"배의 주머니에 하얗고 동그란n돌을 넣고 있다. 사이가 좋아지면n나누어 주는 일도 있다.","language":{"name":"ko","url":"https://pokeapi.co/api/v2/language/3/"},"version":{"name":"sun","url":"https://pokeapi.co/api/v2/version/27/"}},{"flavor_text":"腹部的袋子裡裝著白色的n圓形石頭。如果和牠變得友好，n也可能會分一點給你哦。","language":{"name":"zh-Hant","url":"https://pokeapi.co/api/v2/language/4/"},"version":{"name":"sun","url":"https://pokeapi.co/api/v2/version/27/"}},{"flavor_text":"Il transporte un petit caillou rond et blanc dansnsa poche ventrale. Il arrive même qu’il le donnenaux personnes qu’il aime bien.","language":{"name":"fr","url":"https://pokeapi.co/api/v2/language/5/"},"version":{"name":"sun","url":"https://pokeapi.co/api/v2/version/27/"}},{"flavor_text":"In seinem Beutel trägt es einen runden, weißennStein. Freundet man sich mit ihm an, kann esnvorkommen, dass man ihn geschenkt bekommt.","language":{"name":"de","url":"https://pokeapi.co/api/v2/language/6/"},"version":{"name":"sun","url":"https://pokeapi.co/api/v2/version/27/"}},{"flavor_text":"En la bolsa de su panza transporta una rocanredonda y blanca. Cuando hace amigos puedenllegar a regalársela.","language":{"name":"es","url":"https://pokeapi.co/api/v2/language/7/"},"version":{"name":"sun","url":"https://pokeapi.co/api/v2/version/27/"}},{"flavor_text":"Trasporta nella tasca ventrale una rocciana forma di uovo, che a volte regala ai suoi amici.","language":{"name":"it","url":"https://pokeapi.co/api/v2/language/8/"},"version":{"name":"sun","url":"https://pokeapi.co/api/v2/version/27/"}},{"flavor_text":"It carries a round white rock in its belly pouch.nIf it gets along well with someone, it willnsometimes give that person the rock.","language":{"name":"en","url":"https://pokeapi.co/api/v2/language/9/"},"version":{"name":"sun","url":"https://pokeapi.co/api/v2/version/27/"}},{"flavor_text":"お腹の　袋に　白くて　丸いn石を　入れている。　仲良くなるとnわけて　くれることも　あるよ。","language":{"name":"ja","url":"https://pokeapi.co/api/v2/language/11/"},"version":{"name":"sun","url":"https://pokeapi.co/api/v2/version/27/"}},{"flavor_text":"腹部的袋子里装着白色的n圆形石头。如果关系变好，n也可能会分给你哦。","language":{"name":"zh-Hans","url":"https://pokeapi.co/api/v2/language/12/"},"version":{"name":"sun","url":"https://pokeapi.co/api/v2/version/27/"}},{"flavor_text":"ちいさいので　まだ　タマゴをnうむことが　できない。　かわりにnしろくて　まるい　いしを　さがす。","language":{"name":"ja-Hrkt","url":"https://pokeapi.co/api/v2/language/1/"},"version":{"name":"moon","url":"https://pokeapi.co/api/v2/version/28/"}},{"flavor_text":"작아서 아직 알을n낳을 수 없다. 대신에n하얗고 둥근 돌을 찾는다.","language":{"name":"ko","url":"https://pokeapi.co/api/v2/language/3/"},"version":{"name":"moon","url":"https://pokeapi.co/api/v2/version/28/"}},{"flavor_text":"因為很小，還不能生蛋。n會尋找白白圓圓的n石頭來代替。","language":{"name":"zh-Hant","url":"https://pokeapi.co/api/v2/language/4/"},"version":{"name":"moon","url":"https://pokeapi.co/api/v2/version/28/"}},{"flavor_text":"Comme il est très jeune, il ne peut pas encorenpondre d’œuf. À la place, il cherche un joli petitncaillou blanc, bien rond.","language":{"name":"fr","url":"https://pokeapi.co/api/v2/language/5/"},"version":{"name":"moon","url":"https://pokeapi.co/api/v2/version/28/"}},{"flavor_text":"Es ist noch zu jung, um Eier zu legen. Als Ersatznsucht es nach runden, weißen Steinen.","language":{"name":"de","url":"https://pokeapi.co/api/v2/language/6/"},"version":{"name":"moon","url":"https://pokeapi.co/api/v2/version/28/"}},{"flavor_text":"Como todavía no puede poner huevos, buscanrocas blancas y redondas en su lugar.","language":{"name":"es","url":"https://pokeapi.co/api/v2/language/7/"},"version":{"name":"moon","url":"https://pokeapi.co/api/v2/version/28/"}},{"flavor_text":"Dato che è ancora piccolo e non può deporrenuova, cerca pietre bianche e tonde da usarenin sostituzione.","language":{"name":"it","url":"https://pokeapi.co/api/v2/language/8/"},"version":{"name":"moon","url":"https://pokeapi.co/api/v2/version/28/"}},{"flavor_text":"It’s too small to lay eggs yet. As a surrogate,nit searches out round white stones.","language":{"name":"en","url":"https://pokeapi.co/api/v2/language/9/"},"version":{"name":"moon","url":"https://pokeapi.co/api/v2/version/28/"}},{"flavor_text":"小さいので　まだ　タマゴをn産むことが　できない。　代わりにn白くて　丸い　石を　探す。","language":{"name":"ja","url":"https://pokeapi.co/api/v2/language/11/"},"version":{"name":"moon","url":"https://pokeapi.co/api/v2/version/28/"}},{"flavor_text":"因为很小，还不能生蛋。n会寻找白白的圆圆的n石头来作为替代。","language":{"name":"zh-Hans","url":"https://pokeapi.co/api/v2/language/12/"},"version":{"name":"moon","url":"https://pokeapi.co/api/v2/version/28/"}},{"flavor_text":"おとなしい　ポケモンだが　おなかのnまるい　いしを　とりあげるとnないて　さわいで　おおあばれ。","language":{"name":"ja-Hrkt","url":"https://pokeapi.co/api/v2/language/1/"},"version":{"name":"ultra-sun","url":"https://pokeapi.co/api/v2/version/29/"}},{"flavor_text":"온순한 포켓몬이지만n배의 둥근 돌을 빼내면n울고불고 난폭해진다.","language":{"name":"ko","url":"https://pokeapi.co/api/v2/language/3/"},"version":{"name":"ultra-sun","url":"https://pokeapi.co/api/v2/version/29/"}},{"flavor_text":"性情溫馴的寶可夢，n但如果肚子上的圓形石頭被搶走，n就會哭著大吵大鬧。","language":{"name":"zh-Hant","url":"https://pokeapi.co/api/v2/language/4/"},"version":{"name":"ultra-sun","url":"https://pokeapi.co/api/v2/version/29/"}},{"flavor_text":"C’est un Pokémon d’un naturel calme. Quiconquentente de s’emparer du caillou de sa pochenventrale s’expose toutefois à un gros caprice.","language":{"name":"fr","url":"https://pokeapi.co/api/v2/language/5/"},"version":{"name":"ultra-sun","url":"https://pokeapi.co/api/v2/version/29/"}},{"flavor_text":"Eigentlich ein sehr braves Pokémon, das abernfürchterlich weint und tobt, wenn man dennrunden, weißen Stein aus seinem Beutel nimmt.","language":{"name":"de","url":"https://pokeapi.co/api/v2/language/6/"},"version":{"name":"ultra-sun","url":"https://pokeapi.co/api/v2/version/29/"}},{"flavor_text":"Se trata de un Pokémon dócil y tranquilo, pero,nsi le arrebatan la piedra redonda que lleva en lanbolsa de su panza, se pone a llorar y berrear.","language":{"name":"es","url":"https://pokeapi.co/api/v2/language/7/"},"version":{"name":"ultra-sun","url":"https://pokeapi.co/api/v2/version/29/"}},{"flavor_text":"È un Pokémon docile, ma se si fa per toglierglinla pietra dalla tasca ventrale piange, strilla endiventa una furia.","language":{"name":"it","url":"https://pokeapi.co/api/v2/language/8/"},"version":{"name":"ultra-sun","url":"https://pokeapi.co/api/v2/version/29/"}},{"flavor_text":"Usually it’s a well-behaved Pokémon, but if yountake its round rock away, it will cry and fussnand throw a big old tantrum.","language":{"name":"en","url":"https://pokeapi.co/api/v2/language/9/"},"version":{"name":"ultra-sun","url":"https://pokeapi.co/api/v2/version/29/"}},{"flavor_text":"大人しい　ポケモンだが　お腹のn丸い　石を　取り上げるとn泣いて　騒いで　大暴れ。","language":{"name":"ja","url":"https://pokeapi.co/api/v2/language/11/"},"version":{"name":"ultra-sun","url":"https://pokeapi.co/api/v2/version/29/"}},{"flavor_text":"是非常温顺的宝可梦，n但如果被夺走了腹部的圆石头，n就会哭着大吵大闹。","language":{"name":"zh-Hans","url":"https://pokeapi.co/api/v2/language/12/"},"version":{"name":"ultra-sun","url":"https://pokeapi.co/api/v2/version/29/"}},{"flavor_text":"しろく　まるいものを　みると　はらのnふくろに　しまう。　しまいすぎてnうごけなく　なることも　あるほど。","language":{"name":"ja-Hrkt","url":"https://pokeapi.co/api/v2/language/1/"},"version":{"name":"ultra-moon","url":"https://pokeapi.co/api/v2/version/30/"}},{"flavor_text":"하얗고 둥근 것을 보면 배의n주머니에 넣는다. 너무 많이 넣어서n움직이지 못할 때도 있을 정도다.","language":{"name":"ko","url":"https://pokeapi.co/api/v2/language/3/"},"version":{"name":"ultra-moon","url":"https://pokeapi.co/api/v2/version/30/"}},{"flavor_text":"只要看見又白又圓的東西n就會放進腹部的袋裡。n有時甚至會放得太多而動彈不得。","language":{"name":"zh-Hant","url":"https://pokeapi.co/api/v2/language/4/"},"version":{"name":"ultra-moon","url":"https://pokeapi.co/api/v2/version/30/"}},{"flavor_text":"Dès qu’il repère un objet rond et blanc, il lenrange dans sa poche ventrale. Il en ramassenparfois tellement qu’il ne peut plus bouger.","language":{"name":"fr","url":"https://pokeapi.co/api/v2/language/5/"},"version":{"name":"ultra-moon","url":"https://pokeapi.co/api/v2/version/30/"}},{"flavor_text":"Findet es weiße, runde Steine, verstaut es sie innseinem Beutel. Manchmal trägt es so viele davonnbei sich, dass es nicht mehr laufen kann.","language":{"name":"de","url":"https://pokeapi.co/api/v2/language/6/"},"version":{"name":"ultra-moon","url":"https://pokeapi.co/api/v2/version/30/"}},{"flavor_text":"En cuanto ve cosas blancas y redondas, se lasnguarda en la bolsa de su panza. A veces la llenanhasta tales extremos que no se puede ni mover.","language":{"name":"es","url":"https://pokeapi.co/api/v2/language/7/"},"version":{"name":"ultra-moon","url":"https://pokeapi.co/api/v2/version/30/"}},{"flavor_text":"Quando vede un oggetto bianco e tondo lo mettennella tasca ventrale. A volte ce ne mette cosìntanti che finisce per non riuscire a muoversi.","language":{"name":"it","url":"https://pokeapi.co/api/v2/language/8/"},"version":{"name":"ultra-moon","url":"https://pokeapi.co/api/v2/version/30/"}},{"flavor_text":"When it sees something round and white,nHappiny puts it into the pouch on its stomach. Itnsometimes becomes overloaded and can’t move.","language":{"name":"en","url":"https://pokeapi.co/api/v2/language/9/"},"version":{"name":"ultra-moon","url":"https://pokeapi.co/api/v2/version/30/"}},{"flavor_text":"白く　丸いものを　見ると　腹のn袋に　しまう。　しまいすぎてn動けなく　なることも　あるほど。","language":{"name":"ja","url":"https://pokeapi.co/api/v2/language/11/"},"version":{"name":"ultra-moon","url":"https://pokeapi.co/api/v2/version/30/"}},{"flavor_text":"如果看到又白又圆的东西n就会放到腹部的袋子里。n有时甚至会放得太多而动弹不得。","language":{"name":"zh-Hans","url":"https://pokeapi.co/api/v2/language/12/"},"version":{"name":"ultra-moon","url":"https://pokeapi.co/api/v2/version/30/"}},{"flavor_text":"ラッキーの　まねをして　タマゴにnそっくりな　まるい　いしを　おなかのnふくろに　いれて　だいじにしている。","language":{"name":"ja-Hrkt","url":"https://pokeapi.co/api/v2/language/1/"},"version":{"name":"sword","url":"https://pokeapi.co/api/v2/version/33/"}},{"flavor_text":"럭키를 흉내 내어 알처럼 생긴n둥근 돌을 배의 주머니에 넣고n소중히 보관한다.","language":{"name":"ko","url":"https://pokeapi.co/api/v2/language/3/"},"version":{"name":"sword","url":"https://pokeapi.co/api/v2/version/33/"}},{"flavor_text":"會模仿吉利蛋的樣子，n把很像蛋的渾圓石頭放n在腹部的袋子裡寶貝著。","language":{"name":"zh-Hant","url":"https://pokeapi.co/api/v2/language/4/"},"version":{"name":"sword","url":"https://pokeapi.co/api/v2/version/33/"}},{"flavor_text":"Pour imiter Leveinard, il conserve un caillounen forme d’œuf dans sa poche ventrale etnen prend grand soin.","language":{"name":"fr","url":"https://pokeapi.co/api/v2/language/5/"},"version":{"name":"sword","url":"https://pokeapi.co/api/v2/version/33/"}},{"flavor_text":"Es imitiert Chaneira und legt einen eiförmigennStein in den Beutel an seinem Bauch. Dieser Steinnist sein größter Schatz.","language":{"name":"de","url":"https://pokeapi.co/api/v2/language/6/"},"version":{"name":"sword","url":"https://pokeapi.co/api/v2/version/33/"}},{"flavor_text":"Lleva en la bolsa de su panza una roca con formande huevo que cuida con esmero, imitando anChansey.","language":{"name":"es","url":"https://pokeapi.co/api/v2/language/7/"},"version":{"name":"sword","url":"https://pokeapi.co/api/v2/version/33/"}},{"flavor_text":"Imita Chansey trasportando con cura nella tascanventrale un sasso rotondo identico a un uovo.","language":{"name":"it","url":"https://pokeapi.co/api/v2/language/8/"},"version":{"name":"sword","url":"https://pokeapi.co/api/v2/version/33/"}},{"flavor_text":"Mimicking Chansey, Happiny will place an egg-nshaped stone in its belly pouch. Happiny willntreasure this stone.","language":{"name":"en","url":"https://pokeapi.co/api/v2/language/9/"},"version":{"name":"sword","url":"https://pokeapi.co/api/v2/version/33/"}},{"flavor_text":"ラッキーの　真似をして　タマゴにnそっくりな　まるい　石を　お腹のn袋に　入れて　大事にしている。","language":{"name":"ja","url":"https://pokeapi.co/api/v2/language/11/"},"version":{"name":"sword","url":"https://pokeapi.co/api/v2/version/33/"}},{"flavor_text":"模仿吉利蛋，把很像蛋的n浑圆石头放入腹部的n袋子中用心保管着。","language":{"name":"zh-Hans","url":"https://pokeapi.co/api/v2/language/12/"},"version":{"name":"sword","url":"https://pokeapi.co/api/v2/version/33/"}},{"flavor_text":"なかよくなった　あいてには　だいじなnまるい　いしを　かしてあげる。nかえさないと　なきだし　おおあばれ。","language":{"name":"ja-Hrkt","url":"https://pokeapi.co/api/v2/language/1/"},"version":{"name":"shield","url":"https://pokeapi.co/api/v2/version/34/"}},{"flavor_text":"친해진 상대에게는 소중하게 여기는n둥근 돌을 빌려준다. 돌려주지n않으면 울고불고하다가 난폭해진다.","language":{"name":"ko","url":"https://pokeapi.co/api/v2/language/3/"},"version":{"name":"shield","url":"https://pokeapi.co/api/v2/version/34/"}},{"flavor_text":"會把寶貝的渾圓石頭借給n變得友好的對象。如果不n還給牠的話，就會哭著大鬧。","language":{"name":"zh-Hant","url":"https://pokeapi.co/api/v2/language/4/"},"version":{"name":"shield","url":"https://pokeapi.co/api/v2/version/34/"}},{"flavor_text":"Il prête volontiers son caillou rond à ceuxnqu’il apprécie, mais éclate en sanglots etnse met en colère si on ne le lui rend pas.","language":{"name":"fr","url":"https://pokeapi.co/api/v2/language/5/"},"version":{"name":"shield","url":"https://pokeapi.co/api/v2/version/34/"}},{"flavor_text":"Seinen kostbaren, runden Stein leiht Wonneirannur denjenigen, die es mag. Bekommt es diesennnicht zurück, tobt es und weint bitterlich.","language":{"name":"de","url":"https://pokeapi.co/api/v2/language/6/"},"version":{"name":"shield","url":"https://pokeapi.co/api/v2/version/34/"}},{"flavor_text":"Les deja su preciada roca redonda a aquellosncon los que se lleva bien. Si no se la devuelven,nse echa a llorar, presa de una rabieta.","language":{"name":"es","url":"https://pokeapi.co/api/v2/language/7/"},"version":{"name":"shield","url":"https://pokeapi.co/api/v2/version/34/"}},{"flavor_text":"Dà in prestito il suo amato sasso a chi consideransuo amico, ma se non gli viene restituito piangene si scatena.","language":{"name":"it","url":"https://pokeapi.co/api/v2/language/8/"},"version":{"name":"shield","url":"https://pokeapi.co/api/v2/version/34/"}},{"flavor_text":"Happiny’s willing to lend its precious round stonento those it’s friendly with, but if the stone isn’tnreturned, Happiny will cry and throw a tantrum.","language":{"name":"en","url":"https://pokeapi.co/api/v2/language/9/"},"version":{"name":"shield","url":"https://pokeapi.co/api/v2/version/34/"}},{"flavor_text":"仲良くなった　相手には　大事なn丸い　石を　貸してあげる。n返さないと　泣きだし　大暴れ。","language":{"name":"ja","url":"https://pokeapi.co/api/v2/language/11/"},"version":{"name":"shield","url":"https://pokeapi.co/api/v2/version/34/"}},{"flavor_text":"会把自己珍贵的浑圆石头n借给关系变得很要好的对象。n如果不还给它，它便会大哭大闹。","language":{"name":"zh-Hans","url":"https://pokeapi.co/api/v2/language/12/"},"version":{"name":"shield","url":"https://pokeapi.co/api/v2/version/34/"}}],"form_descriptions":[],"forms_switchable":false,"gender_rate":8,"genera":[{"genus":"ままごとポケモン","language":{"name":"ja-Hrkt","url":"https://pokeapi.co/api/v2/language/1/"}},{"genus":"소꿉놀이포켓몬","language":{"name":"ko","url":"https://pokeapi.co/api/v2/language/3/"}},{"genus":"家家酒寶可夢","language":{"name":"zh-Hant","url":"https://pokeapi.co/api/v2/language/4/"}},{"genus":"Pokémon Maisonjouet","language":{"name":"fr","url":"https://pokeapi.co/api/v2/language/5/"}},{"genus":"Spielhaus","language":{"name":"de","url":"https://pokeapi.co/api/v2/language/6/"}},{"genus":"Pokémon Casita","language":{"name":"es","url":"https://pokeapi.co/api/v2/language/7/"}},{"genus":"Pokémon Ovettino","language":{"name":"it","url":"https://pokeapi.co/api/v2/language/8/"}},{"genus":"Playhouse Pokémon","language":{"name":"en","url":"https://pokeapi.co/api/v2/language/9/"}},{"genus":"ままごとポケモン","language":{"name":"ja","url":"https://pokeapi.co/api/v2/language/11/"}},{"genus":"家家酒宝可梦","language":{"name":"zh-Hans","url":"https://pokeapi.co/api/v2/language/12/"}}],"generation":{"name":"generation-iv","url":"https://pokeapi.co/api/v2/generation/4/"},"growth_rate":{"name":"fast","url":"https://pokeapi.co/api/v2/growth-rate/3/"},"habitat":null,"has_gender_differences":false,"hatch_counter":40,"id":440,"is_baby":true,"is_legendary":false,"is_mythical":false,"name":"happiny","names":[{"language":{"name":"ja-Hrkt","url":"https://pokeapi.co/api/v2/language/1/"},"name":"ピンプク"},{"language":{"name":"roomaji","url":"https://pokeapi.co/api/v2/language/2/"},"name":"Pinpuku"},{"language":{"name":"ko","url":"https://pokeapi.co/api/v2/language/3/"},"name":"핑복"},{"language":{"name":"zh-Hant","url":"https://pokeapi.co/api/v2/language/4/"},"name":"小福蛋"},{"language":{"name":"fr","url":"https://pokeapi.co/api/v2/language/5/"},"name":"Ptiravi"},{"language":{"name":"de","url":"https://pokeapi.co/api/v2/language/6/"},"name":"Wonneira"},{"language":{"name":"es","url":"https://pokeapi.co/api/v2/language/7/"},"name":"Happiny"},{"language":{"name":"it","url":"https://pokeapi.co/api/v2/language/8/"},"name":"Happiny"},{"language":{"name":"en","url":"https://pokeapi.co/api/v2/language/9/"},"name":"Happiny"},{"language":{"name":"ja","url":"https://pokeapi.co/api/v2/language/11/"},"name":"ピンプク"},{"language":{"name":"zh-Hans","url":"https://pokeapi.co/api/v2/language/12/"},"name":"小福蛋"}],"order":126,"pal_park_encounters":[{"area":{"name":"field","url":"https://pokeapi.co/api/v2/pal-park-area/2/"},"base_score":50,"rate":30}],"pokedex_numbers":[{"entry_number":440,"pokedex":{"name":"national","url":"https://pokeapi.co/api/v2/pokedex/1/"}},{"entry_number":96,"pokedex":{"name":"original-sinnoh","url":"https://pokeapi.co/api/v2/pokedex/5/"}},{"entry_number":96,"pokedex":{"name":"extended-sinnoh","url":"https://pokeapi.co/api/v2/pokedex/6/"}},{"entry_number":32,"pokedex":{"name":"original-alola","url":"https://pokeapi.co/api/v2/pokedex/16/"}},{"entry_number":32,"pokedex":{"name":"original-melemele","url":"https://pokeapi.co/api/v2/pokedex/17/"}},{"entry_number":16,"pokedex":{"name":"original-akala","url":"https://pokeapi.co/api/v2/pokedex/18/"}},{"entry_number":15,"pokedex":{"name":"original-ulaula","url":"https://pokeapi.co/api/v2/pokedex/19/"}},{"entry_number":8,"pokedex":{"name":"original-poni","url":"https://pokeapi.co/api/v2/pokedex/20/"}},{"entry_number":39,"pokedex":{"name":"updated-alola","url":"https://pokeapi.co/api/v2/pokedex/21/"}},{"entry_number":39,"pokedex":{"name":"updated-melemele","url":"https://pokeapi.co/api/v2/pokedex/22/"}},{"entry_number":16,"pokedex":{"name":"updated-akala","url":"https://pokeapi.co/api/v2/pokedex/23/"}},{"entry_number":15,"pokedex":{"name":"updated-ulaula","url":"https://pokeapi.co/api/v2/pokedex/24/"}},{"entry_number":15,"pokedex":{"name":"updated-poni","url":"https://pokeapi.co/api/v2/pokedex/25/"}},{"entry_number":6,"pokedex":{"name":"isle-of-armor","url":"https://pokeapi.co/api/v2/pokedex/28/"}}],"shape":{"name":"humanoid","url":"https://pokeapi.co/api/v2/pokemon-shape/12/"},"varieties":[{"is_default":true,"pokemon":{"name":"happiny","url":"https://pokeapi.co/api/v2/pokemon/440/"}}]}