{"base_happiness":70,"capture_rate":255,"color":{"name":"white","url":"https://pokeapi.co/api/v2/pokemon-color/9/"},"egg_groups":[{"name":"mineral","url":"https://pokeapi.co/api/v2/egg-group/10/"}],"evolution_chain":{"url":"https://pokeapi.co/api/v2/evolution-chain/296/"},"evolves_from_species":null,"flavor_text_entries":[{"flavor_text":"Il exhale une haleine à -50 °C.nIl fabrique des cristaux de neigenet fait neiger autour de lui.","language":{"name":"fr","url":"https://pokeapi.co/api/v2/language/5/"},"version":{"name":"black","url":"https://pokeapi.co/api/v2/version/17/"}},{"flavor_text":"The temperature of their breathnis -58° F. They create snow crystals andnmake snow fall in the areas around them.","language":{"name":"en","url":"https://pokeapi.co/api/v2/language/9/"},"version":{"name":"black","url":"https://pokeapi.co/api/v2/version/17/"}},{"flavor_text":"Ce Pokémon est né d’un glaçon quina baigné dans la lumière du matin.nIl se cache dans la neige pour dormir.","language":{"name":"fr","url":"https://pokeapi.co/api/v2/language/5/"},"version":{"name":"white","url":"https://pokeapi.co/api/v2/version/18/"}},{"flavor_text":"This Pokémon formed from iciclesnbathed in energy from the morning sun.nIt sleeps buried in snow.","language":{"name":"en","url":"https://pokeapi.co/api/v2/language/9/"},"version":{"name":"white","url":"https://pokeapi.co/api/v2/version/18/"}},{"flavor_text":"Theoretically, this Pokémon formed fromnicicles bathed in energy from the morningnsun. Their breath is -58° F.","language":{"name":"en","url":"https://pokeapi.co/api/v2/language/9/"},"version":{"name":"black-2","url":"https://pokeapi.co/api/v2/version/21/"}},{"flavor_text":"Theoretically, this Pokémon formed fromnicicles bathed in energy from the morningnsun. Their breath is -58° F.","language":{"name":"en","url":"https://pokeapi.co/api/v2/language/9/"},"version":{"name":"white-2","url":"https://pokeapi.co/api/v2/version/22/"}},{"flavor_text":"マイナス５０どの　いきを　はく。nゆきの　けっしょうを　つくってnあたりに　ゆきを　ふらせる。","language":{"name":"ja-Hrkt","url":"https://pokeapi.co/api/v2/language/1/"},"version":{"name":"x","url":"https://pokeapi.co/api/v2/version/23/"}},{"flavor_text":"마이너스 50도의 숨결을 내뱉는다.n눈 결정을 만들어n주변에 눈이 내리게 한다.","language":{"name":"ko","url":"https://pokeapi.co/api/v2/language/3/"},"version":{"name":"x","url":"https://pokeapi.co/api/v2/version/23/"}},{"flavor_text":"Il exhale une haleine à -50 °C. Il fabrique des cristauxnde neige et fait neiger autour de lui.","language":{"name":"fr","url":"https://pokeapi.co/api/v2/language/5/"},"version":{"name":"x","url":"https://pokeapi.co/api/v2/version/23/"}},{"flavor_text":"Die Temperatur seines Odems liegt bei -50 °C.nEs erzeugt Eiskristalle und lässt es in seinernUmgebung schneien.","language":{"name":"de","url":"https://pokeapi.co/api/v2/language/6/"},"version":{"name":"x","url":"https://pokeapi.co/api/v2/version/23/"}},{"flavor_text":"Lanza un aliento de -50 °C. Crea bloques de nieve ynes capaz de lograr que nieve a su alrededor.","language":{"name":"es","url":"https://pokeapi.co/api/v2/language/7/"},"version":{"name":"x","url":"https://pokeapi.co/api/v2/version/23/"}},{"flavor_text":"Il suo fiato è a -50 °C. Fa nevicare tutto intorno,nformando dei cristalli di neve.","language":{"name":"it","url":"https://pokeapi.co/api/v2/language/8/"},"version":{"name":"x","url":"https://pokeapi.co/api/v2/version/23/"}},{"flavor_text":"The temperature of their breath is -58 degreesnFahrenheit. They create snow crystals and makensnow fall in the areas around them.","language":{"name":"en","url":"https://pokeapi.co/api/v2/language/9/"},"version":{"name":"x","url":"https://pokeapi.co/api/v2/version/23/"}},{"flavor_text":"マイナス５０度の　息を　吐く。n雪の　結晶を　作ってnあたりに　雪を　降らせる。","language":{"name":"ja","url":"https://pokeapi.co/api/v2/language/11/"},"version":{"name":"x","url":"https://pokeapi.co/api/v2/version/23/"}},{"flavor_text":"あさひの　エネルギーを　あびたnつららが　ポケモンに　なった。nゆきに　からだを　うめて　ねむる。","language":{"name":"ja-Hrkt","url":"https://pokeapi.co/api/v2/language/1/"},"version":{"name":"y","url":"https://pokeapi.co/api/v2/version/24/"}},{"flavor_text":"아침 해의 에너지를 받은n고드름이 포켓몬이 되었다.n눈에 몸을 묻고 잠든다.","language":{"name":"ko","url":"https://pokeapi.co/api/v2/language/3/"},"version":{"name":"y","url":"https://pokeapi.co/api/v2/version/24/"}},{"flavor_text":"Ce Pokémon est né d’un glaçon qui a baigné dansnla lumière du matin. Il se cache dans la neige pourndormir.","language":{"name":"fr","url":"https://pokeapi.co/api/v2/language/5/"},"version":{"name":"y","url":"https://pokeapi.co/api/v2/version/24/"}},{"flavor_text":"Ein Eiszapfen, der durch die Energie der aufgehendennSonne zum Pokémon wurde. Nachts deckt es sich mitnSchnee zu.","language":{"name":"de","url":"https://pokeapi.co/api/v2/language/6/"},"version":{"name":"y","url":"https://pokeapi.co/api/v2/version/24/"}},{"flavor_text":"Nació de un carámbano que absorbió la energía delnsol al alba. Duerme arropado por la nieve.","language":{"name":"es","url":"https://pokeapi.co/api/v2/language/7/"},"version":{"name":"y","url":"https://pokeapi.co/api/v2/version/24/"}},{"flavor_text":"Pokémon nato da una stalattite che ha ricevutonl’energia del sole mattutino. Dorme sepolto sottonla neve.","language":{"name":"it","url":"https://pokeapi.co/api/v2/language/8/"},"version":{"name":"y","url":"https://pokeapi.co/api/v2/version/24/"}},{"flavor_text":"This Pokémon formed from icicles bathed in energynfrom the morning sun. It sleeps buried in snow.","language":{"name":"en","url":"https://pokeapi.co/api/v2/language/9/"},"version":{"name":"y","url":"https://pokeapi.co/api/v2/version/24/"}},{"flavor_text":"朝日の　エネルギーを　浴びたnつららが　ポケモンに　なった。n雪に　体を　埋めて　眠る。","language":{"name":"ja","url":"https://pokeapi.co/api/v2/language/11/"},"version":{"name":"y","url":"https://pokeapi.co/api/v2/version/24/"}},{"flavor_text":"マイナス５０どの　いきを　はく。nゆきの　けっしょうを　つくってnあたりに　ゆきを　ふらせる。","language":{"name":"ja-Hrkt","url":"https://pokeapi.co/api/v2/language/1/"},"version":{"name":"omega-ruby","url":"https://pokeapi.co/api/v2/version/25/"}},{"flavor_text":"마이너스 50도의 숨결을 내뱉는다.n눈 결정을 만들어n주변에 눈이 내리게 한다.","language":{"name":"ko","url":"https://pokeapi.co/api/v2/language/3/"},"version":{"name":"omega-ruby","url":"https://pokeapi.co/api/v2/version/25/"}},{"flavor_text":"Il exhale une haleine à -50 °C. Il fabrique des cristaux de neigenet fait neiger autour de lui.","language":{"name":"fr","url":"https://pokeapi.co/api/v2/language/5/"},"version":{"name":"omega-ruby","url":"https://pokeapi.co/api/v2/version/25/"}},{"flavor_text":"Die Temperatur seines Odems liegt bei -50 °C. Es erzeugtnEiskristalle und lässt es in seiner Umgebung schneien.","language":{"name":"de","url":"https://pokeapi.co/api/v2/language/6/"},"version":{"name":"omega-ruby","url":"https://pokeapi.co/api/v2/version/25/"}},{"flavor_text":"Lanza un aliento de -50 °C. Crea bloques de nieve y es capaznde lograr que nieve a su alrededor.","language":{"name":"es","url":"https://pokeapi.co/api/v2/language/7/"},"version":{"name":"omega-ruby","url":"https://pokeapi.co/api/v2/version/25/"}},{"flavor_text":"Il suo fiato è a -50 °C. Fa nevicare tutto intorno, formandondei cristalli di neve.","language":{"name":"it","url":"https://pokeapi.co/api/v2/language/8/"},"version":{"name":"omega-ruby","url":"https://pokeapi.co/api/v2/version/25/"}},{"flavor_text":"The temperature of their breath is -58 degreesnFahrenheit. They create snow crystals and makensnow fall in the areas around them.","language":{"name":"en","url":"https://pokeapi.co/api/v2/language/9/"},"version":{"name":"omega-ruby","url":"https://pokeapi.co/api/v2/version/25/"}},{"flavor_text":"マイナス５０度の　息を　吐く。n雪の　結晶を　作ってnあたりに　雪を　降らせる。","language":{"name":"ja","url":"https://pokeapi.co/api/v2/language/11/"},"version":{"name":"omega-ruby","url":"https://pokeapi.co/api/v2/version/25/"}},{"flavor_text":"あさひの　エネルギーを　あびたnつららが　ポケモンに　なった。nゆきに　からだを　うめて　ねむる。","language":{"name":"ja-Hrkt","url":"https://pokeapi.co/api/v2/language/1/"},"version":{"name":"alpha-sapphire","url":"https://pokeapi.co/api/v2/version/26/"}},{"flavor_text":"아침 해의 에너지를 받은n고드름이 포켓몬이 되었다.n눈에 몸을 묻고 잠든다.","language":{"name":"ko","url":"https://pokeapi.co/api/v2/language/3/"},"version":{"name":"alpha-sapphire","url":"https://pokeapi.co/api/v2/version/26/"}},{"flavor_text":"Ce Pokémon est né d’un glaçon qui a baigné dans la lumièrendu matin. Il se cache dans la neige pour dormir.","language":{"name":"fr","url":"https://pokeapi.co/api/v2/language/5/"},"version":{"name":"alpha-sapphire","url":"https://pokeapi.co/api/v2/version/26/"}},{"flavor_text":"Ein Eiszapfen, der durch die Energie der aufgehenden Sonnenzum Pokémon wurde. Nachts deckt es sich mit Schnee zu.","language":{"name":"de","url":"https://pokeapi.co/api/v2/language/6/"},"version":{"name":"alpha-sapphire","url":"https://pokeapi.co/api/v2/version/26/"}},{"flavor_text":"Nació de un carámbano que absorbió la energía del sol alnalba. Duerme arropado por la nieve.","language":{"name":"es","url":"https://pokeapi.co/api/v2/language/7/"},"version":{"name":"alpha-sapphire","url":"https://pokeapi.co/api/v2/version/26/"}},{"flavor_text":"Pokémon nato da una stalattite che ha ricevuto l’energia delnsole mattutino. Dorme sepolto sotto la neve.","language":{"name":"it","url":"https://pokeapi.co/api/v2/language/8/"},"version":{"name":"alpha-sapphire","url":"https://pokeapi.co/api/v2/version/26/"}},{"flavor_text":"This Pokémon formed from icicles bathed in energynfrom the morning sun. It sleeps buried in snow.","language":{"name":"en","url":"https://pokeapi.co/api/v2/language/9/"},"version":{"name":"alpha-sapphire","url":"https://pokeapi.co/api/v2/version/26/"}},{"flavor_text":"朝日の　エネルギーを　浴びたnつららが　ポケモンに　なった。n雪に　体を　埋めて　眠る。","language":{"name":"ja","url":"https://pokeapi.co/api/v2/language/11/"},"version":{"name":"alpha-sapphire","url":"https://pokeapi.co/api/v2/version/26/"}},{"flavor_text":"つららから　うまれた　ポケモン。nつめたい　いきで　ゆきの　けっしょうをnつくって　ゆきを　ふらせる。","language":{"name":"ja-Hrkt","url":"https://pokeapi.co/api/v2/language/1/"},"version":{"name":"sun","url":"https://pokeapi.co/api/v2/version/27/"}},{"flavor_text":"고드름에서 태어난 포켓몬이다.n차가운 숨으로 눈 결정을n만들어 눈을 뿌린다.","language":{"name":"ko","url":"https://pokeapi.co/api/v2/language/3/"},"version":{"name":"sun","url":"https://pokeapi.co/api/v2/version/27/"}},{"flavor_text":"從冰柱中誕生的寶可夢。n用冰冷的氣息製造雪的結晶，n讓周圍降雪。","language":{"name":"zh-Hant","url":"https://pokeapi.co/api/v2/language/4/"},"version":{"name":"sun","url":"https://pokeapi.co/api/v2/version/27/"}},{"flavor_text":"Né dans une colonne de glace, ce Pokémonnpeut créer des flocons de neige de son soufflenglacé, voire même faire tomber la neige en été.","language":{"name":"fr","url":"https://pokeapi.co/api/v2/language/5/"},"version":{"name":"sun","url":"https://pokeapi.co/api/v2/version/27/"}},{"flavor_text":"Dieses Pokémon ist aus einem Eiszapfennentstanden. Mit seinem kalten Odem erzeugtnes Eiskristalle und lässt es schneien.","language":{"name":"de","url":"https://pokeapi.co/api/v2/language/6/"},"version":{"name":"sun","url":"https://pokeapi.co/api/v2/version/27/"}},{"flavor_text":"Pokémon nacido de un carámbano. Con sunaliento gélido es capaz de crear cristales dennieve y provocar una nevasca.","language":{"name":"es","url":"https://pokeapi.co/api/v2/language/7/"},"version":{"name":"sun","url":"https://pokeapi.co/api/v2/version/27/"}},{"flavor_text":"Pokémon nato da una stalattite di ghiaccio.nCon il suo fiato gelido forma dei cristallindi neve e fa nevicare.","language":{"name":"it","url":"https://pokeapi.co/api/v2/language/8/"},"version":{"name":"sun","url":"https://pokeapi.co/api/v2/version/27/"}},{"flavor_text":"Born of an icicle, this Pokémon uses its frostynbreath to make ice crystals, causing snownto fall.","language":{"name":"en","url":"https://pokeapi.co/api/v2/language/9/"},"version":{"name":"sun","url":"https://pokeapi.co/api/v2/version/27/"}},{"flavor_text":"氷柱から　生まれたポケモン。n冷たい　息で　雪の　結晶をnつくって　雪を　降らせる。","language":{"name":"ja","url":"https://pokeapi.co/api/v2/language/11/"},"version":{"name":"sun","url":"https://pokeapi.co/api/v2/version/27/"}},{"flavor_text":"从冰柱中诞生的宝可梦。n用冰冷的气息制造雪的结晶，n让天上下雪。","language":{"name":"zh-Hans","url":"https://pokeapi.co/api/v2/language/12/"},"version":{"name":"sun","url":"https://pokeapi.co/api/v2/version/27/"}},{"flavor_text":"だきしめると　ひんやり　ここちよい。nあつい　ちほうでは　いっかに　１ぴきとnちょうほうされる　ポケモンだ。","language":{"name":"ja-Hrkt","url":"https://pokeapi.co/api/v2/language/1/"},"version":{"name":"moon","url":"https://pokeapi.co/api/v2/version/28/"}},{"flavor_text":"껴안으면 차가워서 기분이 좋다.n더운 지방에서는 한 집에 1마리씩 두고n소중하게 여기는 포켓몬이다.","language":{"name":"ko","url":"https://pokeapi.co/api/v2/language/3/"},"version":{"name":"moon","url":"https://pokeapi.co/api/v2/version/28/"}},{"flavor_text":"抱緊牠就會感覺涼涼的n非常舒服。在炎熱的地區，n是每家必備１隻的便利寶可夢。","language":{"name":"zh-Hant","url":"https://pokeapi.co/api/v2/language/4/"},"version":{"name":"moon","url":"https://pokeapi.co/api/v2/version/28/"}},{"flavor_text":"Serrer Sorbébé contre soi procure une délicieusensensation de fraîcheur. Dans les régionsnchaudes, c’est le Pokémon à avoir à la maison.","language":{"name":"fr","url":"https://pokeapi.co/api/v2/language/5/"},"version":{"name":"moon","url":"https://pokeapi.co/api/v2/version/28/"}},{"flavor_text":"Wenn man es umarmt, fühlt es sich angenehmnund kühl an. In heißen Regionen hat man daherngern ein Exemplar im Haus.","language":{"name":"de","url":"https://pokeapi.co/api/v2/language/6/"},"version":{"name":"moon","url":"https://pokeapi.co/api/v2/version/28/"}},{"flavor_text":"Al abrazarlo transmite una sensación agradableny refrescante. La gente que vive en las regionesncálidas aprecia mucho su presencia en casa.","language":{"name":"es","url":"https://pokeapi.co/api/v2/language/7/"},"version":{"name":"moon","url":"https://pokeapi.co/api/v2/version/28/"}},{"flavor_text":"Abbracciarlo dà una piacevole sensazionendi freschezza. Per chi vive in regioni calde, èndecisamente un Pokémon da tenere in casa.","language":{"name":"it","url":"https://pokeapi.co/api/v2/language/8/"},"version":{"name":"moon","url":"https://pokeapi.co/api/v2/version/28/"}},{"flavor_text":"It feels pleasantly cool when embraced. ThisnPokémon is treasured by households innwarm regions.","language":{"name":"en","url":"https://pokeapi.co/api/v2/language/9/"},"version":{"name":"moon","url":"https://pokeapi.co/api/v2/version/28/"}},{"flavor_text":"抱きしめると　ひんやり　心地よい。n暑い　地方では　一家に　１匹とn重宝される　ポケモンだ。","language":{"name":"ja","url":"https://pokeapi.co/api/v2/language/11/"},"version":{"name":"moon","url":"https://pokeapi.co/api/v2/version/28/"}},{"flavor_text":"抱紧的话，就会感觉凉凉的n非常舒服。在炎热地区，n是每家必备１只的便利宝可梦。","language":{"name":"zh-Hans","url":"https://pokeapi.co/api/v2/language/12/"},"version":{"name":"moon","url":"https://pokeapi.co/api/v2/version/28/"}},{"flavor_text":"マイナス　５０どの　れいきを　はく。nあたたかい　ばしょに　いるとnちょっとずつ　ちいさくなって　いく。","language":{"name":"ja-Hrkt","url":"https://pokeapi.co/api/v2/language/1/"},"version":{"name":"ultra-sun","url":"https://pokeapi.co/api/v2/version/29/"}},{"flavor_text":"마이너스 50도 냉기를 내뱉는다.n따듯한 장소에 있으면n조금씩 작아진다.","language":{"name":"ko","url":"https://pokeapi.co/api/v2/language/3/"},"version":{"name":"ultra-sun","url":"https://pokeapi.co/api/v2/version/29/"}},{"flavor_text":"會吐出零下５０度的寒氣。n如果待在溫暖的地方，n身體就會漸漸地變小。","language":{"name":"zh-Hant","url":"https://pokeapi.co/api/v2/language/4/"},"version":{"name":"ultra-sun","url":"https://pokeapi.co/api/v2/version/29/"}},{"flavor_text":"Son souffle glacé descend jusqu’à -50 °C.nIl fond peu à peu quand il se retrouve dansnun endroit chaud.","language":{"name":"fr","url":"https://pokeapi.co/api/v2/language/5/"},"version":{"name":"ultra-sun","url":"https://pokeapi.co/api/v2/version/29/"}},{"flavor_text":"Die Temperatur seines Atems liegt bei -50 °C.nWenn es sich an warmen Orten aufhält, wird esnnach und nach kleiner.","language":{"name":"de","url":"https://pokeapi.co/api/v2/language/6/"},"version":{"name":"ultra-sun","url":"https://pokeapi.co/api/v2/version/29/"}},{"flavor_text":"Exhala vaho a una temperatura de -50 ºC. Suntamaño corporal se reduce poco a poco cuandonse encuentra en un lugar cálido.","language":{"name":"es","url":"https://pokeapi.co/api/v2/language/7/"},"version":{"name":"ultra-sun","url":"https://pokeapi.co/api/v2/version/29/"}},{"flavor_text":"Il suo fiato ha una temperatura di -50 °C.nQuando si trova in un luogo caldo, il volumendel suo corpo si riduce a poco a poco.","language":{"name":"it","url":"https://pokeapi.co/api/v2/language/8/"},"version":{"name":"ultra-sun","url":"https://pokeapi.co/api/v2/version/29/"}},{"flavor_text":"It exhales cold air that is at –58 degreesnFahrenheit. When it’s in a warm place, it shrinksnlittle by little.","language":{"name":"en","url":"https://pokeapi.co/api/v2/language/9/"},"version":{"name":"ultra-sun","url":"https://pokeapi.co/api/v2/version/29/"}},{"flavor_text":"マイナス　５０度の　冷気を　吐く。n暖かい　場所に　いるとnちょっとずつ　小さくなって　いく。","language":{"name":"ja","url":"https://pokeapi.co/api/v2/language/11/"},"version":{"name":"ultra-sun","url":"https://pokeapi.co/api/v2/version/29/"}},{"flavor_text":"会吐出零下５０度的冷气。n如果呆在温暖的场所，n就会一点点地变小。","language":{"name":"zh-Hans","url":"https://pokeapi.co/api/v2/language/12/"},"version":{"name":"ultra-sun","url":"https://pokeapi.co/api/v2/version/29/"}},{"flavor_text":"あさひを　あびる　つららが　まだnとけたくないと　ねがい　うまれた。nよるは　ゆきに　もぐって　ねむる。","language":{"name":"ja-Hrkt","url":"https://pokeapi.co/api/v2/language/1/"},"version":{"name":"ultra-moon","url":"https://pokeapi.co/api/v2/version/30/"}},{"flavor_text":"아침 햇살을 받은 고드름이 아직n녹고 싶지 않다고 소원하여 태어났다.n밤에는 눈 속에 들어가 잠든다.","language":{"name":"ko","url":"https://pokeapi.co/api/v2/language/3/"},"version":{"name":"ultra-moon","url":"https://pokeapi.co/api/v2/version/30/"}},{"flavor_text":"誕生自沐浴在朝陽下的n冰柱還不願融化的心意。n夜裡會潛進雪中睡覺。","language":{"name":"zh-Hant","url":"https://pokeapi.co/api/v2/language/4/"},"version":{"name":"ultra-moon","url":"https://pokeapi.co/api/v2/version/30/"}},{"flavor_text":"Il est né d’une stalactite de glace qui, face aunsoleil du matin, a fait le vœu de ne pas fondre.nIl se terre dans la neige pour dormir la nuit.","language":{"name":"fr","url":"https://pokeapi.co/api/v2/language/5/"},"version":{"name":"ultra-moon","url":"https://pokeapi.co/api/v2/version/30/"}},{"flavor_text":"Es entstand aus dem Wunsch eines Eiszapfens,nder in der Morgensonne nicht schmelzen wollte.nNachts schläft es tief vergraben im Schnee.","language":{"name":"de","url":"https://pokeapi.co/api/v2/language/6/"},"version":{"name":"ultra-moon","url":"https://pokeapi.co/api/v2/version/30/"}},{"flavor_text":"Nació a partir del deseo de una estalactita denno derretirse con los rayos del albor. Por lannoche se arropa bajo la nieve para dormir.","language":{"name":"es","url":"https://pokeapi.co/api/v2/language/7/"},"version":{"name":"ultra-moon","url":"https://pokeapi.co/api/v2/version/30/"}},{"flavor_text":"È nato dal desiderio di una stalattite che nonnvoleva sciogliersi ai raggi del sole mattutino.nLa notte dorme immerso nella neve.","language":{"name":"it","url":"https://pokeapi.co/api/v2/language/8/"},"version":{"name":"ultra-moon","url":"https://pokeapi.co/api/v2/version/30/"}},{"flavor_text":"When the morning sun hit an icicle, it wished notnto melt, and thus Vanillite was born. At night, itnburies itself in snow to sleep.","language":{"name":"en","url":"https://pokeapi.co/api/v2/language/9/"},"version":{"name":"ultra-moon","url":"https://pokeapi.co/api/v2/version/30/"}},{"flavor_text":"朝日を　浴びる　つららが　まだn溶けたくないと　願い　生まれた。n夜は　雪に　潜って　眠る。","language":{"name":"ja","url":"https://pokeapi.co/api/v2/language/11/"},"version":{"name":"ultra-moon","url":"https://pokeapi.co/api/v2/version/30/"}},{"flavor_text":"是由沐浴在朝阳下但仍不愿n融化的冰柱诞生而成。n晚上会潜入雪中睡觉。","language":{"name":"zh-Hans","url":"https://pokeapi.co/api/v2/language/12/"},"version":{"name":"ultra-moon","url":"https://pokeapi.co/api/v2/version/30/"}},{"flavor_text":"あつい　とちでは　くらせない。nれいきを　はいて　ゆきを　ふらせnつもった　なかに　もぐって　ねむる。","language":{"name":"ja-Hrkt","url":"https://pokeapi.co/api/v2/language/1/"},"version":{"name":"sword","url":"https://pokeapi.co/api/v2/version/33/"}},{"flavor_text":"더운 곳에서는 살 수 없다.n냉기를 뿜어 눈을 내리게 한 뒤n쌓인 눈 속에 들어가 잠든다.","language":{"name":"ko","url":"https://pokeapi.co/api/v2/language/3/"},"version":{"name":"sword","url":"https://pokeapi.co/api/v2/version/33/"}},{"flavor_text":"無法在炎熱的地方生存。n會吐出冷氣來降雪，n然後窩在積雪裡睡覺。","language":{"name":"zh-Hant","url":"https://pokeapi.co/api/v2/language/4/"},"version":{"name":"sword","url":"https://pokeapi.co/api/v2/version/33/"}},{"flavor_text":"Il ne peut pas vivre dans les contrées chaudes.nIl souffle un air glacial pour faire tomber la neige,npuis s’y plonge pour dormir.","language":{"name":"fr","url":"https://pokeapi.co/api/v2/language/5/"},"version":{"name":"sword","url":"https://pokeapi.co/api/v2/version/33/"}},{"flavor_text":"Gelatini kann nicht an warmen Orten leben. Esnerzeugt Schnee, indem es kalte Luft ausatmet,nund vergräbt sich dann darin, um zu schlafen.","language":{"name":"de","url":"https://pokeapi.co/api/v2/language/6/"},"version":{"name":"sword","url":"https://pokeapi.co/api/v2/version/33/"}},{"flavor_text":"No puede vivir en lugares muy cálidos. Provocannevadas exhalando un vaho gélido y luego senacurruca en la nieve acumulada para dormir.","language":{"name":"es","url":"https://pokeapi.co/api/v2/language/7/"},"version":{"name":"sword","url":"https://pokeapi.co/api/v2/version/33/"}},{"flavor_text":"Non può vivere nei luoghi caldi. Fa nevicarenesalando un alito gelido e poi si addormentanimmerso nella neve che si è accumulata.","language":{"name":"it","url":"https://pokeapi.co/api/v2/language/8/"},"version":{"name":"sword","url":"https://pokeapi.co/api/v2/version/33/"}},{"flavor_text":"Unable to survive in hot areas, it makes itselfncomfortable by breathing out air cold enough toncause snow. It burrows into the snow to sleep.","language":{"name":"en","url":"https://pokeapi.co/api/v2/language/9/"},"version":{"name":"sword","url":"https://pokeapi.co/api/v2/version/33/"}},{"flavor_text":"暑い　土地では　暮らせない。n冷気を　吐いて　雪を　降らせn積もった　中に　潜って　眠る。","language":{"name":"ja","url":"https://pokeapi.co/api/v2/language/11/"},"version":{"name":"sword","url":"https://pokeapi.co/api/v2/version/33/"}},{"flavor_text":"无法在炎热的地方生存。n会吐出冷气来降雪，n然后窝在积雪里睡觉。","language":{"name":"zh-Hans","url":"https://pokeapi.co/api/v2/language/12/"},"version":{"name":"sword","url":"https://pokeapi.co/api/v2/version/33/"}},{"flavor_text":"つららから　うまれたと　いわれる。nマイナス５０どの　れいきを　はいてnあたりを　こおらせ　すみやすくする。","language":{"name":"ja-Hrkt","url":"https://pokeapi.co/api/v2/language/1/"},"version":{"name":"shield","url":"https://pokeapi.co/api/v2/version/34/"}},{"flavor_text":"고드름에서 태어났다고 전해진다.n마이너스 50도의 냉기를 뿜어n주변을 얼려 살기 좋게 만든다.","language":{"name":"ko","url":"https://pokeapi.co/api/v2/language/3/"},"version":{"name":"shield","url":"https://pokeapi.co/api/v2/version/34/"}},{"flavor_text":"據說牠是從冰柱中誕生的。n為了能讓自己生活得更舒適，n會吐出零下５０度的冷氣凍住四周。","language":{"name":"zh-Hant","url":"https://pokeapi.co/api/v2/language/4/"},"version":{"name":"shield","url":"https://pokeapi.co/api/v2/version/34/"}},{"flavor_text":"On raconte qu’il est né de stalactites.nIl gèle les alentours en soufflant de l’air à - 50 °Cnpour améliorer son confort.","language":{"name":"fr","url":"https://pokeapi.co/api/v2/language/5/"},"version":{"name":"shield","url":"https://pokeapi.co/api/v2/version/34/"}},{"flavor_text":"Es entstand angeblich aus einem Eiszapfen undnspeit -50 ºC kalte Luft aus, um die Umgebungnauf seine Wohlfühltemperatur abzukühlen.","language":{"name":"de","url":"https://pokeapi.co/api/v2/language/6/"},"version":{"name":"shield","url":"https://pokeapi.co/api/v2/version/34/"}},{"flavor_text":"Este Pokémon nació a partir de un carámbano.nExhala un vaho a -50 °C con el que congela elnambiente para adaptarlo a sus necesidades.","language":{"name":"es","url":"https://pokeapi.co/api/v2/language/7/"},"version":{"name":"shield","url":"https://pokeapi.co/api/v2/version/34/"}},{"flavor_text":"Si dice che sia nato da una stalattite di ghiaccio.nPer crearsi un habitat adatto, congela l’ambientenintorno con il suo fiato a -50 ºC.","language":{"name":"it","url":"https://pokeapi.co/api/v2/language/8/"},"version":{"name":"shield","url":"https://pokeapi.co/api/v2/version/34/"}},{"flavor_text":"Supposedly, this Pokémon was born from annicicle. It spews out freezing air at −58 degreesnFahrenheit to make itself more comfortable.","language":{"name":"en","url":"https://pokeapi.co/api/v2/language/9/"},"version":{"name":"shield","url":"https://pokeapi.co/api/v2/version/34/"}},{"flavor_text":"氷柱から　生まれたと　いわれる。nマイナス５０度の　冷気を　吐いてnあたりを　凍らせ　棲みやすくする。","language":{"name":"ja","url":"https://pokeapi.co/api/v2/language/11/"},"version":{"name":"shield","url":"https://pokeapi.co/api/v2/version/34/"}},{"flavor_text":"据说它是从冰柱中诞生的。n为了能让自己生活得更舒适，n会吐出零下５０度的冷气冻住四周。","language":{"name":"zh-Hans","url":"https://pokeapi.co/api/v2/language/12/"},"version":{"name":"shield","url":"https://pokeapi.co/api/v2/version/34/"}}],"form_descriptions":[],"forms_switchable":false,"gender_rate":4,"genera":[{"genus":"しんせつポケモン","language":{"name":"ja-Hrkt","url":"https://pokeapi.co/api/v2/language/1/"}},{"genus":"신설포켓몬","language":{"name":"ko","url":"https://pokeapi.co/api/v2/language/3/"}},{"genus":"新雪寶可夢","language":{"name":"zh-Hant","url":"https://pokeapi.co/api/v2/language/4/"}},{"genus":"Pokémon Poudreuse","language":{"name":"fr","url":"https://pokeapi.co/api/v2/language/5/"}},{"genus":"Neuschnee","language":{"name":"de","url":"https://pokeapi.co/api/v2/language/6/"}},{"genus":"Pokémon Nieve Fresca","language":{"name":"es","url":"https://pokeapi.co/api/v2/language/7/"}},{"genus":"Pokémon Nevefresca","language":{"name":"it","url":"https://pokeapi.co/api/v2/language/8/"}},{"genus":"Fresh Snow Pokémon","language":{"name":"en","url":"https://pokeapi.co/api/v2/language/9/"}},{"genus":"しんせつポケモン","language":{"name":"ja","url":"https://pokeapi.co/api/v2/language/11/"}},{"genus":"新雪宝可梦","language":{"name":"zh-Hans","url":"https://pokeapi.co/api/v2/language/12/"}}],"generation":{"name":"generation-v","url":"https://pokeapi.co/api/v2/generation/5/"},"growth_rate":{"name":"slow","url":"https://pokeapi.co/api/v2/growth-rate/1/"},"habitat":null,"has_gender_differences":false,"hatch_counter":20,"id":582,"is_baby":false,"is_legendary":false,"is_mythical":false,"name":"vanillite","names":[{"language":{"name":"ja-Hrkt","url":"https://pokeapi.co/api/v2/language/1/"},"name":"バニプッチ"},{"language":{"name":"ko","url":"https://pokeapi.co/api/v2/language/3/"},"name":"바닐프티"},{"language":{"name":"zh-Hant","url":"https://pokeapi.co/api/v2/language/4/"},"name":"迷你冰"},{"language":{"name":"fr","url":"https://pokeapi.co/api/v2/language/5/"},"name":"Sorbébé"},{"language":{"name":"de","url":"https://pokeapi.co/api/v2/language/6/"},"name":"Gelatini"},{"language":{"name":"es","url":"https://pokeapi.co/api/v2/language/7/"},"name":"Vanillite"},{"language":{"name":"it","url":"https://pokeapi.co/api/v2/language/8/"},"name":"Vanillite"},{"language":{"name":"en","url":"https://pokeapi.co/api/v2/language/9/"},"name":"Vanillite"},{"language":{"name":"ja","url":"https://pokeapi.co/api/v2/language/11/"},"name":"バニプッチ"},{"language":{"name":"zh-Hans","url":"https://pokeapi.co/api/v2/language/12/"},"name":"迷你冰"}],"order":583,"pal_park_encounters":[],"pokedex_numbers":[{"entry_number":582,"pokedex":{"name":"national","url":"https://pokeapi.co/api/v2/pokedex/1/"}},{"entry_number":88,"pokedex":{"name":"original-unova","url":"https://pokeapi.co/api/v2/pokedex/8/"}},{"entry_number":255,"pokedex":{"name":"updated-unova","url":"https://pokeapi.co/api/v2/pokedex/9/"}},{"entry_number":85,"pokedex":{"name":"kalos-mountain","url":"https://pokeapi.co/api/v2/pokedex/14/"}},{"entry_number":255,"pokedex":{"name":"original-alola","url":"https://pokeapi.co/api/v2/pokedex/16/"}},{"entry_number":127,"pokedex":{"name":"original-ulaula","url":"https://pokeapi.co/api/v2/pokedex/19/"}},{"entry_number":332,"pokedex":{"name":"updated-alola","url":"https://pokeapi.co/api/v2/pokedex/21/"}},{"entry_number":153,"pokedex":{"name":"updated-ulaula","url":"https://pokeapi.co/api/v2/pokedex/24/"}},{"entry_number":72,"pokedex":{"name":"galar","url":"https://pokeapi.co/api/v2/pokedex/27/"}},{"entry_number":22,"pokedex":{"name":"crown-tundra","url":"https://pokeapi.co/api/v2/pokedex/29/"}}],"shape":{"name":"blob","url":"https://pokeapi.co/api/v2/pokemon-shape/5/"},"varieties":[{"is_default":true,"pokemon":{"name":"vanillite","url":"https://pokeapi.co/api/v2/pokemon/582/"}}]}